terraform.py
terraform_binary-0.11.11.post1.data/data/lib/terraform
terraform_binary-0.11.11.post1.dist-info/METADATA
terraform_binary-0.11.11.post1.dist-info/RECORD
terraform_binary-0.11.11.post1.dist-info/WHEEL
terraform_binary-0.11.11.post1.dist-info/entry_points.txt
terraform_binary-0.11.11.post1.dist-info/top_level.txt
