Metadata-Version: 2.1
Name: terraform-binary
Version: 0.11.11.post1
Summary: Python wrapper for Terraform
Home-page: https://github.com/sourcelair/terraform-binary/
Author: Paris Kasidiaris
Author-email: paris@sourcelair.com
License: UNKNOWN
Platform: UNKNOWN
